<?xml version="1.0" encoding="utf-8" ?><dwsync><file name="AdvButton.as" server="ftp.ericbeltran.com//ericbeltran/" local="3242072408" remote="1791871302757447188" /><file name="MoreMath.as" server="ftp.ericbeltran.com//ericbeltran/" local="3241826234" remote="1791871302757447188" /><file name="Slider.as" server="ftp.ericbeltran.com//ericbeltran/" local="3242257420" remote="1791871302757447188" /><file name="Slider.fla" server="ftp.ericbeltran.com//ericbeltran/" local="3242257914" remote="1791871302757447188" /><file name="SomethingNew.as" server="ftp.ericbeltran.com//ericbeltran/" local="3241822976" remote="1791871302757447188" /><file name="TextAnim.as" server="ftp.ericbeltran.com//ericbeltran/" local="3242167530" remote="1791871302757447188" /><file name="TextEffect.as" server="ftp.ericbeltran.com//ericbeltran/" local="3242167522" remote="1791871302757447188" /><file name="ToggleButton.as" server="ftp.ericbeltran.com//ericbeltran/" local="3242078654" remote="1791871302757447188" /><file name="TypeThis.as" server="ftp.ericbeltran.com//ericbeltran/" local="3241827926" remote="1791871302757447188" /></dwsync>